mirobot/__init__.py
mirobot/base_mirobot.py
mirobot/base_rover.py
mirobot/bluetooth_low_energy_interface.py
mirobot/exceptions.py
mirobot/extended_dataclasses.py
mirobot/mirobot.py
mirobot/mirobot_status.py
mirobot/serial_device.py
mirobot/serial_interface.py
mirobot/resources/__init__.py
mirobot/resources/reset.xml
mirobot_py-1.0.52.dist-info/LICENSE
mirobot_py-1.0.52.dist-info/METADATA
mirobot_py-1.0.52.dist-info/WHEEL
mirobot_py-1.0.52.dist-info/top_level.txt
mirobot_py-1.0.52.dist-info/RECORD
